<?xml version="1.0" encoding="windows-1252" ?>
<adfc-config xmlns="http://xmlns.oracle.com/adf/controller" version="1.2">
  <task-flow-definition id="fti-file-merge-share-detail-dealer-flow">
    <default-activity>FtiFileMergeShareDealer</default-activity>
    <view id="FtiFileMergeShareDealer">
      <page>/tmFragments/FtiFileMergeShareDealer.jsff</page>
    </view>
    <view id="FtiFileMergeShareDetailDealer">
      <page>/tmFragments/FtiFileMergeShareDetailDealer.jsff</page>
    </view>
    <view id="FtiFileMergeDealerShareProcessedData">
      <page>/tmFragments/FtiFileMergeDealerShareProcessedData.jsff</page>
    </view>
    <control-flow-rule id="__1">
      <from-activity-id>FtiFileMergeShareDealer</from-activity-id>
      <control-flow-case id="__2">
        <from-outcome>goDetail</from-outcome>
        <to-activity-id>FtiFileMergeShareDetailDealer</to-activity-id>
      </control-flow-case>
    </control-flow-rule>
    <control-flow-rule id="__3">
      <from-activity-id>FtiFileMergeShareDetailDealer</from-activity-id>
      <control-flow-case id="__4">
        <from-outcome>goBack</from-outcome>
        <to-activity-id>FtiFileMergeShareDealer</to-activity-id>
      </control-flow-case>
      <control-flow-case id="__5">
        <from-outcome>goProcessedData</from-outcome>
        <to-activity-id>FtiFileMergeDealerShareProcessedData</to-activity-id>
      </control-flow-case>
    </control-flow-rule>
    <control-flow-rule id="__6">
      <from-activity-id>FtiFileMergeDealerShareProcessedData</from-activity-id>
      <control-flow-case id="__7">
        <from-outcome>back</from-outcome>
        <to-activity-id>FtiFileMergeShareDetailDealer</to-activity-id>
      </control-flow-case>
    </control-flow-rule>
    <use-page-fragments/>
  </task-flow-definition>
</adfc-config>
